hey_cli/__init__.py
hey_cli/hey.py
hey_cli/src/__init__.py
hey_cli/src/config.py
hey_cli/src/ai/__init__.py
hey_cli/src/ai/client.py
hey_cli/src/ai/prompts.py
hey_cli/src/ai/response.py
hey_cli/src/core/__init__.py
hey_cli/src/core/history.py
hey_cli/src/core/indexer.py
hey_cli/src/core/operations.py
hey_cli/src/models/__init__.py
hey_cli/src/models/operations.py
hey_cli/src/models/schema.py
hey_cli/src/utils/__init__.py
hey_cli/src/utils/display.py
hey_cli/src/utils/parsing.py
hey_python-1.0.3.dist-info/LICENSE.rst
hey_python-1.0.3.dist-info/METADATA
hey_python-1.0.3.dist-info/WHEEL
hey_python-1.0.3.dist-info/entry_points.txt
hey_python-1.0.3.dist-info/top_level.txt
hey_python-1.0.3.dist-info/RECORD
