Metadata-Version: 2.1
Name: hey_python
Version: 1.0.3
Summary: An AI-powered CLI assistant that helps with coding and system tasks
Home-page: https://github.com/Kawai-Senpai/hey-python
Author: Ranit Bhowmick
Author-email: bhowmickranitking@duck.com
License: MIT
Classifier: Development Status :: 4 - Beta
Classifier: Intended Audience :: Developers
Classifier: License :: OSI Approved :: MIT License
Classifier: Programming Language :: Python :: 3
Classifier: Programming Language :: Python :: 3.8
Classifier: Programming Language :: Python :: 3.9
Classifier: Programming Language :: Python :: 3.10
Classifier: Programming Language :: Python :: 3.11
Requires-Python: >=3.8
License-File: LICENSE.rst
Requires-Dist: openai>=1.0.0
Requires-Dist: ultraprint>=3.0.0
Requires-Dist: python-dotenv>=0.15.0
Requires-Dist: pydantic>=2.0.0
Requires-Dist: keyring>=24.0.0
Requires-Dist: cryptography>=36.0.0
